<?xml version="1.0" encoding="utf-8"?><waypoints>
	<!-- #  1 --><waypoint x="-8427" z="45023" y="744">	</waypoint>
	<!-- #  2 --><waypoint x="-8535" z="45109" y="744">	</waypoint>
	<!-- #  3 --><waypoint x="-8595" z="45203" y="744">	</waypoint>
	<!-- #  4 --><waypoint x="-8721" z="45465" y="744">	</waypoint>
	<!-- #  5 --><waypoint x="-8888" z="45485" y="744">	</waypoint>
	<!-- #  6 --><waypoint x="-8830" z="45498" y="744">	</waypoint>
	<!-- #  7 --><waypoint x="-8722" z="45550" y="744">	</waypoint>
	<!-- #  8 --><waypoint x="-8722" z="45653" y="751">	</waypoint>
	<!-- #  9 --><waypoint x="-8720" z="45776" y="758">	</waypoint>
	<!-- # 10 --><waypoint x="-8679" z="45796" y="760">	</waypoint>
	<!-- # 11 --><waypoint x="-8526" z="45819" y="774">	</waypoint>
	<!-- # 12 --><waypoint x="-8419" z="45827" y="777">	</waypoint>
	<!-- # 13 --><waypoint x="-8302" z="45823" y="773">	</waypoint>
	<!-- # 14 --><waypoint x="-8255" z="45800" y="768">	</waypoint>
	<!-- # 15 --><waypoint x="-8222" z="45788" y="765">	</waypoint>
	<!-- # 16 --><waypoint x="-8139" z="45767" y="763">	</waypoint>
	<!-- # 17 --><waypoint x="-8037" z="45741" y="763">	</waypoint>
	<!-- # 18 --><waypoint x="-7955" z="45721" y="765">	</waypoint>
	<!-- # 19 --><waypoint x="-7943" z="45685" y="763">	</waypoint>
	<!-- # 20 --><waypoint x="-7931" z="45646" y="744">	</waypoint>
	<!-- # 21 --><waypoint x="-7918" z="45594" y="744">	</waypoint>
	<!-- # 22 --><waypoint x="-7880" z="45502" y="744">	</waypoint>
	<!-- # 23 --><waypoint x="-7854" z="45414" y="744">	</waypoint>
	<!-- # 24 --><waypoint x="-7853" z="45342" y="744">	</waypoint>
	<!-- # 25 --><waypoint x="-7869" z="45281" y="744">	</waypoint>
	<!-- # 26 --><waypoint x="-7882" z="45227" y="744">	</waypoint>
	<!-- # 27 --><waypoint x="-7899" z="45158" y="744">	</waypoint>
	<!-- # 28 --><waypoint x="-7920" z="45132" y="744">	</waypoint>
	<!-- # 29 --><waypoint x="-7977" z="45115" y="744">	</waypoint>
	<!-- # 30 --><waypoint x="-8099" z="45084" y="744">	</waypoint>
	<!-- # 31 --><waypoint x="-8226" z="45047" y="744">	</waypoint>
	<!-- # 32 --><waypoint x="-8427" z="45010" y="744">	</waypoint>
</waypoints>